[
  {
    "marketing": {
      "trackingCode": "12789120xa"
    },
    "_id": "3061603ID",
    "eventType": "Experience Event",
    "timestamp": "2014-09-15 13:52:02"
  },
  {
    "marketing": {
      "trackingCode": "12789120xa"
    },
    "_id": "6488873ID",
    "eventType": "Experience Event",
    "timestamp": "2016-01-29 06:10:21"
  },
  {
    "marketing": {
      "trackingCode": "18971098xd"
    },
    "_id": "4438381ID",
    "eventType": "Experience Event",
    "timestamp": "2015-12-24 06:02:55"
  },
  {
    "marketing": {
      "trackingCode": "18971098xd"
    },
    "_id": "1366737ID",
    "eventType": "Experience Event",
    "timestamp": "2015-12-11 17:47:46"
  },
  {
    "marketing": {
      "trackingCode": "19098701xc"
    },
    "_id": "5706022ID",
    "eventType": "Experience Event",
    "timestamp": "2018-08-13 18:49:51"
  },
  {
    "marketing": {
      "trackingCode": "12789120xa"
    },
    "_id": "5307720ID",
    "eventType": "Experience Event",
    "timestamp": "2016-12-12 03:42:16"
  },
  {
    "marketing": {
      "trackingCode": "19098701xc"
    },
    "_id": "3168130ID",
    "eventType": "Experience Event",
    "timestamp": "2019-01-20 14:45:51"
  },
  {
    "marketing": {
      "trackingCode": "18971098xd"
    },
    "_id": "4282181ID",
    "eventType": "Experience Event",
    "timestamp": "2016-08-02 19:09:26"
  },
  {
    "marketing": {
      "trackingCode": "12789120xa"
    },
    "_id": "5204516ID",
    "eventType": "Experience Event",
    "timestamp": "2016-07-03 03:59:17"
  },
  {
    "marketing": {
      "trackingCode": "19098701xc"
    },
    "_id": "3508993ID",
    "eventType": "Experience Event",
    "timestamp": "2015-09-29 09:38:04"
  },
  {
    "marketing": {
      "trackingCode": "19098701xc"
    },
    "_id": "1774879ID",
    "eventType": "Experience Event",
    "timestamp": "2016-02-16 06:48:47"
  },
  {
    "marketing": {
      "trackingCode": "18971098xd"
    },
    "_id": "9694755ID",
    "eventType": "Experience Event",
    "timestamp": "2014-08-28 01:32:59"
  },
  {
    "marketing": {
      "trackingCode": "18971098xd"
    },
    "_id": "9235727ID",
    "eventType": "Experience Event",
    "timestamp": "2016-10-21 01:04:37"
  },
  {
    "marketing": {
      "trackingCode": "19098701xc"
    },
    "_id": "5499733ID",
    "eventType": "Experience Event",
    "timestamp": "2018-05-10 09:37:01"
  },
  {
    "marketing": {
      "trackingCode": "19098701xc"
    },
    "_id": "6229633ID",
    "eventType": "Experience Event",
    "timestamp": "2015-09-18 23:12:17"
  },
  {
    "marketing": {
      "trackingCode": "18971098xd"
    },
    "_id": "2621241ID",
    "eventType": "Experience Event",
    "timestamp": "2016-03-10 18:53:27"
  },
  {
    "marketing": {
      "trackingCode": "19098701xc"
    },
    "_id": "8762234ID",
    "eventType": "Experience Event",
    "timestamp": "2015-06-08 20:42:30"
  },
  {
    "marketing": {
      "trackingCode": "19098701xc"
    },
    "_id": "3937156ID",
    "eventType": "Experience Event",
    "timestamp": "2018-02-18 23:27:52"
  },
  {
    "marketing": {
      "trackingCode": "19098701xc"
    },
    "_id": "4611939ID",
    "eventType": "Experience Event",
    "timestamp": "2014-12-10 14:36:31"
  },
  {
    "marketing": {
      "trackingCode": "18971098xd"
    },
    "_id": "4683978ID",
    "eventType": "Experience Event",
    "timestamp": "2016-06-08 05:44:12"
  },
  {
    "marketing": {
      "trackingCode": "12789120xa"
    },
    "_id": "4696393ID",
    "eventType": "Experience Event",
    "timestamp": "2015-01-15 09:02:38"
  },
  {
    "marketing": {
      "trackingCode": "12789120xa"
    },
    "_id": "3735695ID",
    "eventType": "Experience Event",
    "timestamp": "2017-09-20 04:42:29"
  },
  {
    "marketing": {
      "trackingCode": "19098701xc"
    },
    "_id": "5682018ID",
    "eventType": "Experience Event",
    "timestamp": "2016-03-02 21:09:03"
  },
  {
    "marketing": {
      "trackingCode": "18971098xd"
    },
    "_id": "6824424ID",
    "eventType": "Experience Event",
    "timestamp": "2016-06-16 18:25:26"
  },
  {
    "marketing": {
      "trackingCode": "12789120xa"
    },
    "_id": "8796447ID",
    "eventType": "Experience Event",
    "timestamp": "2016-05-04 20:57:22"
  },
  {
    "marketing": {
      "trackingCode": "18971098xd"
    },
    "_id": "7034901ID",
    "eventType": "Experience Event",
    "timestamp": "2018-07-02 00:46:32"
  },
  {
    "marketing": {
      "trackingCode": "12789120xa"
    },
    "_id": "8286327ID",
    "eventType": "Experience Event",
    "timestamp": "2015-11-05 16:07:21"
  },
  {
    "marketing": {
      "trackingCode": "18971098xd"
    },
    "_id": "8136735ID",
    "eventType": "Experience Event",
    "timestamp": "2014-12-20 01:44:18"
  },
  {
    "marketing": {
      "trackingCode": "19098701xc"
    },
    "_id": "7592667ID",
    "eventType": "Experience Event",
    "timestamp": "2017-07-19 16:19:10"
  },
  {
    "marketing": {
      "trackingCode": "19098701xc"
    },
    "_id": "1740738ID",
    "eventType": "Experience Event",
    "timestamp": "2019-02-04 01:52:37"
  },
  {
    "marketing": {
      "trackingCode": "19098701xc"
    },
    "_id": "9938178ID",
    "eventType": "Experience Event",
    "timestamp": "2014-02-20 00:18:13"
  },
  {
    "marketing": {
      "trackingCode": "19098701xc"
    },
    "_id": "9349651ID",
    "eventType": "Experience Event",
    "timestamp": "2018-03-30 07:37:04"
  },
  {
    "marketing": {
      "trackingCode": "12789120xa"
    },
    "_id": "1561868ID",
    "eventType": "Experience Event",
    "timestamp": "2016-05-25 14:13:44"
  },
  {
    "marketing": {
      "trackingCode": "19098701xc"
    },
    "_id": "5102101ID",
    "eventType": "Experience Event",
    "timestamp": "2015-05-05 20:16:50"
  },
  {
    "marketing": {
      "trackingCode": "18971098xd"
    },
    "_id": "9820536ID",
    "eventType": "Experience Event",
    "timestamp": "2014-10-01 04:18:57"
  },
  {
    "marketing": {
      "trackingCode": "12789120xa"
    },
    "_id": "7913492ID",
    "eventType": "Experience Event",
    "timestamp": "2014-05-23 13:30:32"
  },
  {
    "marketing": {
      "trackingCode": "18971098xd"
    },
    "_id": "1549272ID",
    "eventType": "Experience Event",
    "timestamp": "2015-03-08 04:58:05"
  },
  {
    "marketing": {
      "trackingCode": "12789120xa"
    },
    "_id": "3879475ID",
    "eventType": "Experience Event",
    "timestamp": "2015-09-01 04:35:46"
  },
  {
    "marketing": {
      "trackingCode": "19098701xc"
    },
    "_id": "8554156ID",
    "eventType": "Experience Event",
    "timestamp": "2014-05-10 13:34:11"
  },
  {
    "marketing": {
      "trackingCode": "19098701xc"
    },
    "_id": "8651235ID",
    "eventType": "Experience Event",
    "timestamp": "2015-10-07 20:15:13"
  },
  {
    "marketing": {
      "trackingCode": "12789120xa"
    },
    "_id": "6822961ID",
    "eventType": "Experience Event",
    "timestamp": "2019-03-28 02:41:11"
  },
  {
    "marketing": {
      "trackingCode": "12789120xa"
    },
    "_id": "9729515ID",
    "eventType": "Experience Event",
    "timestamp": "2015-12-09 19:37:12"
  },
  {
    "marketing": {
      "trackingCode": "18971098xd"
    },
    "_id": "8181425ID",
    "eventType": "Experience Event",
    "timestamp": "2016-12-11 15:07:19"
  },
  {
    "marketing": {
      "trackingCode": "12789120xa"
    },
    "_id": "6578013ID",
    "eventType": "Experience Event",
    "timestamp": "2018-08-17 14:39:51"
  },
  {
    "marketing": {
      "trackingCode": "18971098xd"
    },
    "_id": "2329707ID",
    "eventType": "Experience Event",
    "timestamp": "2015-12-08 07:10:10"
  },
  {
    "marketing": {
      "trackingCode": "18971098xd"
    },
    "_id": "9566274ID",
    "eventType": "Experience Event",
    "timestamp": "2015-05-30 05:49:18"
  },
  {
    "marketing": {
      "trackingCode": "12789120xa"
    },
    "_id": "7016630ID",
    "eventType": "Experience Event",
    "timestamp": "2018-03-14 17:18:31"
  },
  {
    "marketing": {
      "trackingCode": "19098701xc"
    },
    "_id": "6625383ID",
    "eventType": "Experience Event",
    "timestamp": "2017-02-26 05:11:43"
  },
  {
    "marketing": {
      "trackingCode": "12789120xa"
    },
    "_id": "4959490ID",
    "eventType": "Experience Event",
    "timestamp": "2015-06-29 20:33:29"
  },
  {
    "marketing": {
      "trackingCode": "12789120xa"
    },
    "_id": "2848825ID",
    "eventType": "Experience Event",
    "timestamp": "2014-12-10 20:01:56"
  }
]